CHANGES.rst
CONTRIBUTORS.rst
DEVELOP.rst
LICENSE.rst
MANIFEST.in
README.rst
setup.cfg
setup.py
docs/index.rst
src/operun/__init__.py
src/operun.crm.egg-info/PKG-INFO
src/operun.crm.egg-info/SOURCES.txt
src/operun.crm.egg-info/dependency_links.txt
src/operun.crm.egg-info/entry_points.txt
src/operun.crm.egg-info/namespace_packages.txt
src/operun.crm.egg-info/not-zip-safe
src/operun.crm.egg-info/requires.txt
src/operun.crm.egg-info/top_level.txt
src/operun/crm/__init__.py
src/operun/crm/config.py
src/operun/crm/configure.zcml
src/operun/crm/interfaces.py
src/operun/crm/setuphandlers.py
src/operun/crm/testing.py
src/operun/crm/browser/__init__.py
src/operun/crm/browser/account.py
src/operun/crm/browser/accounts.py
src/operun/crm/browser/configure.zcml
src/operun/crm/browser/contact.py
src/operun/crm/browser/contacts.py
src/operun/crm/browser/dashboard.py
src/operun/crm/browser/modal_edit.py
src/operun/crm/browser/vcard.py
src/operun/crm/browser/images/account-16.png
src/operun/crm/browser/images/accounts-16.png
src/operun/crm/browser/images/accounts-64.png
src/operun/crm/browser/images/contact-16.png
src/operun/crm/browser/images/contacts-16.png
src/operun/crm/browser/images/contacts-64.png
src/operun/crm/browser/images/files-16.png
src/operun/crm/browser/images/files-64.png
src/operun/crm/browser/images/invoice-16.png
src/operun/crm/browser/images/offer-16.png
src/operun/crm/browser/images/todo-16.png
src/operun/crm/browser/images/todos-16.png
src/operun/crm/browser/overrides/.gitkeep
src/operun/crm/browser/static/.gitkeep
src/operun/crm/browser/templates/account.pt
src/operun/crm/browser/templates/accounts.pt
src/operun/crm/browser/templates/contact.pt
src/operun/crm/browser/templates/contacts.pt
src/operun/crm/browser/templates/dashboard.pt
src/operun/crm/browser/templates/modal_edit.pt
src/operun/crm/content/__init__.py
src/operun/crm/content/account.py
src/operun/crm/content/accounts.py
src/operun/crm/content/contact.py
src/operun/crm/content/contacts.py
src/operun/crm/content/invoice.py
src/operun/crm/content/offer.py
src/operun/crm/content/todo.py
src/operun/crm/content/todos.py
src/operun/crm/events/__init__.py
src/operun/crm/events/configure.zcml
src/operun/crm/events/event_handlers.py
src/operun/crm/ldap/__init__.py
src/operun/crm/ldap/configure.zcml
